{
	"eyebrow": "Legal role",
	"title": "Mandate at a glance",
	"paragraphs": [
		"CPMR operates within Ghana’s policy framework for traditional and herbal medicines. Its work supports regulators, health facilities, and communities with evidence, training, and quality-oriented services.",
		"The Centre’s mandate covers research, technical services, and capacity building so that plant-based medicines are developed and used with appropriate safeguards and public accountability."
	],
	"cta": {
		"label": "Read mandate and governance",
		"href": "/about/"
	}
}
